{
"type": "FeatureCollection",
"name": "Isleta_police_____",
"crs": { "type": "name", "properties": { "name": "urn:ogc:def:crs:OGC:1.3:CRS84" } },
"features": [
{ "type": "Feature", "properties": { "name": "police" }, "geometry": { "type": "Point", "coordinates": [ -106.665690100217944, 34.929500080264518, 0.0 ] } }
]
}
