{
"type": "FeatureCollection",
"name": "isleta_specialpoints_school",
"crs": { "type": "name", "properties": { "name": "urn:ogc:def:crs:OGC:1.3:CRS84" } },
"features": [
{ "type": "Feature", "properties": { "submission_ID": "1097fd69-bd9f-4e39-b38b-382819824516", "Condition_of_the_Artwork": "Excellent (Less than 5% damage)", "Type_of_Artwork": "Mural", "Primary_Location_of_Artwork": "Public Utility/Infrastructure", "Secondary_Location_of_Artwork__": "", "Type_Your_3_Initials_or_Assigne": "Dmm" }, "geometry": { "type": "Point", "coordinates": [ -106.709157463412282, 34.905492885154935 ] } },
{ "type": "Feature", "properties": { "submission_ID": "c55a3c07-70e8-4fcb-b2eb-5f48201243cb", "Condition_of_the_Artwork": "Excellent (Less than 5% damage)", "Type_of_Artwork": "Mural", "Primary_Location_of_Artwork": "Roadside", "Secondary_Location_of_Artwork__": "", "Type_Your_3_Initials_or_Assigne": "SJS " }, "geometry": { "type": "Point", "coordinates": [ -106.709729609896428, 34.904483738861011 ] } },
{ "type": "Feature", "properties": { "submission_ID": "706b2b88-0c7e-461f-9e22-025bb9ad7144", "Condition_of_the_Artwork": "Excellent (Less than 5% damage)", "Type_of_Artwork": "Mural", "Primary_Location_of_Artwork": "Roadside", "Secondary_Location_of_Artwork__": "Residential", "Type_Your_3_Initials_or_Assigne": "SJS " }, "geometry": { "type": "Point", "coordinates": [ -106.719474409938314, 34.902564283461068 ] } },
{ "type": "Feature", "properties": { "submission_ID": "f349530f-f322-4ba7-a20c-5a873976b6bb", "Condition_of_the_Artwork": "Good (11-20% damage)", "Type_of_Artwork": "Mural", "Primary_Location_of_Artwork": "Roadside", "Secondary_Location_of_Artwork__": "", "Type_Your_3_Initials_or_Assigne": "SJS " }, "geometry": { "type": "Point", "coordinates": [ -106.721928630557613, 34.902643871376391 ] } },
{ "type": "Feature", "properties": { "submission_ID": "f2f0cb73-0d7a-40bd-bc78-7a73f1ad1e06", "Condition_of_the_Artwork": "Excellent (Less than 5% damage)", "Type_of_Artwork": "Mural", "Primary_Location_of_Artwork": "School", "Secondary_Location_of_Artwork__": "", "Type_Your_3_Initials_or_Assigne": "SJS " }, "geometry": { "type": "Point", "coordinates": [ -106.723132935040681, 34.89812229614764 ] } },
{ "type": "Feature", "properties": { "submission_ID": "672987a9-0eca-43ec-8646-761966248027", "Condition_of_the_Artwork": "Excellent (Less than 5% damage)", "Type_of_Artwork": "Mural", "Primary_Location_of_Artwork": "School", "Secondary_Location_of_Artwork__": "", "Type_Your_3_Initials_or_Assigne": "SJS " }, "geometry": { "type": "Point", "coordinates": [ -106.723162625953066, 34.898076840237074 ] } },
{ "type": "Feature", "properties": { "submission_ID": "9cb438df-af93-4cde-a85b-83b3a667948b", "Condition_of_the_Artwork": "Excellent (Less than 5% damage)", "Type_of_Artwork": "Sculpture/Installations", "Primary_Location_of_Artwork": "Business/Commercial", "Secondary_Location_of_Artwork__": "", "Type_Your_3_Initials_or_Assigne": "SJS " }, "geometry": { "type": "Point", "coordinates": [ -106.72147181719329, 34.897498848937488 ] } }
]
}
